README.md
setup.py
cwlgen/__init__.py
cwlgen/commandlinebinding.py
cwlgen/commandlinetool.py
cwlgen/common.py
cwlgen/import_cwl.py
cwlgen/requirements.py
cwlgen/utils.py
cwlgen/version.py
cwlgen/workflow.py
cwlgen/workflowdeps.py
cwlgen.egg-info/PKG-INFO
cwlgen.egg-info/SOURCES.txt
cwlgen.egg-info/dependency_links.txt
cwlgen.egg-info/requires.txt
cwlgen.egg-info/top_level.txt
test/test_export.py
test/test_unit_cwlgen.py
test/test_unit_import_tool.py
test/test_unit_import_workflow.py
test/test_unit_requirements.py
test/test_unit_typing.py
test/test_unit_workflow.py